{"url": "https://thuvienphapluat.vn/hoi-dap-phap-luat/2BC25-hd-quy-trinh-thanh-toan-uy-nhiem-thu.html", "data": [{"question": "Quy trình thanh toán ủy nhiệm thu được quy định như thế nào? Văn bản nào quy định điều này?", "answer": "Quy trình thanh toán ủy nhiệm thu được quy định tại Khoản 2 Điều 9 Thông tư 46/2014/TT-NHNN hướng dẫn về dịch vụ thanh toán không dùng tiền mặt do Thống đốc Ngân hàng Nhà nước ban hành. Ngân hàng xây dựng, ban hành quy trình nội bộ thực hiện thanh toán ủy nhiệm thu, đảm bảo xử lý nhanh chóng, chính xác, an toàn và đầy đủ các bước sau: \n\na) Lập, giao nhận ủy nhiệm thu;\nb) Kiểm soát ủy nhiệm thu;\nc) Xử lý chứng từ và hạch toán;\nd) Ngân hàng thực hiện báo Nợ, báo Có đầy đủ, kịp thời cho khách hàng theo phương thức, thời điểm báo Nợ, báo Có đã được thỏa thuận giữa ngân hàng và khách hàng phù hợp với quy định của pháp luật."}], "extras": {"page": 252}}