{"url": "https://thuvienphapluat.vn/hoi-dap-phap-luat/418CE-hd-nhung-ca-nhan-nao-duoc-su-dung-ngoai-te-tien-mat-tai-viet-nam.html", "data": [{"question": "Những cá nhân nào được phép sử dụng ngoại tệ tiền mặt tại Việt Nam?", "answer": "Người cư trú và người không cư trú (cư dân Việt Nam và người nước ngoài) có ngoại tệ tiền mặt được phép cất giữ, mang theo người, cho, tặng, thừa kế, bán cho tổ chức tín dụng được phép, chuyển hoặc mang ra nước ngoài, và thanh toán cho các đối tượng được phép thu ngoại tệ tiền mặt. Ngoài ra, người cư trú có thể sử dụng ngoại tệ tiền mặt để gửi tiết kiệm ngoại tệ tại tổ chức tín dụng được phép và rút tiền gốc, lãi bằng đồng tiền đã gửi.\n\nĐiều 13 Nghị định 70/2014/NĐ-CP và Điều 3 Thông tư 20/2011/TT-NHNN quy định chi tiết về vấn đề này."}], "extras": {"page": 163}}