{"url": "https://thuvienphapluat.vn/hoi-dap-phap-luat/38FDA-hd-tai-khoan-thuc-hien-bao-lanh-cua-chi-nhanh-ngan-hang-nuoc-ngoai-cho-nguoi-khong-cu-tru.html", "data": [{"question": "Tài khoản thực hiện bảo lãnh của chi nhánh ngân hàng nước ngoài cho người không cư trú được quy định như thế nào?", "answer": "Điều 16 Thông tư 37/2013/TT-NHNN hướng dẫn về quản lý ngoại hối đối với việc cho vay ra nước ngoài và thu hồi nợ bảo lãnh cho người không cư trú do Thống đốc Ngân hàng Nhà nước Việt Nam ban hành quy định: Tổ chức tín dụng, chi nhánh ngân hàng nước ngoài là bên bảo lãnh cho người không cư trú có trách nhiệm thực hiện việc theo dõi các giao dịch liên quan đến việc thực hiện bảo lãnh và thu hồi nợ bảo lãnh qua tài khoản theo đúng các quy định hiện hành về hạch toán, kế toán đối với tổ chức tín dụng, chi nhánh ngân hàng nước ngoài; chịu trách nhiệm và đảm bảo thực hiện các giao dịch liên quan đến bảo lãnh và thu hồi nợ bảo lãnh theo đúng nội dung văn bản của Ngân hàng Nhà nước xác nhận đăng ký, đăng ký thay đổi khoản thu hồi nợ bảo lãnh của tổ chức tín dụng, chi nhánh ngân hàng nước ngoài."}], "extras": {"page": 233}}