{"url": "https://thuvienphapluat.vn/hoi-dap-phap-luat/28FEA-hd-tieu-chi-xep-hang-va-diem-doi-voi-quy-tin-dung-nhan-dan-bao-gom-nhung-gi.html", "data": [{"question": "Tiêu chí xếp hạng và điểm đối với quỹ tín dụng nhân dân bao gồm những gì?", "answer": "Tổng điểm cho các tiêu chí xếp hạng là 100 điểm và điểm phân bổ cho từng tiêu chí như sau:\n1. Vốn: 10 điểm.\n2. Chất lượng tài sản: 30 điểm.\n3. Năng lực quản trị, điều hành, kiểm soát: 30 điểm.\n4. Kết quả hoạt động kinh doanh: 10 điểm.\n5. Khả năng chi trả: 20 điểm.\n\nTiêu chí xếp hạng và điểm đối với quỹ tín dụng nhân dân được quy định tại Thông tư 42/2016/TT-NHNN quy định xếp hạng quỹ tín dụng nhân dân."}], "extras": {"page": 398}}