{"url": "https://thuvienphapluat.vn/hoi-dap-phap-luat/22B99-hd-sai-lech-thong-tin-tai-khoan-thi-xu-ly-nhu-the-nao.html", "data": [{"question": "Khi có sự sai lệch thông tin tài khoản, khách hàng cần làm gì để giải quyết vấn đề?", "answer": "Khi phát hiện sai sót về thông tin tài khoản, khách hàng nên báo ngay cho tổ chức phát hành thẻ để tiến hành xử lý. Điều 20 Thông tư 19/2016/TT-NHNN quy định về hoạt động thẻ ngân hàng, cụ thể như sau:\n- Khách hàng có quyền yêu cầu tổ chức phát hành thẻ tra soát khi phát hiện có sai sót hoặc nghi ngờ có sai sót về giao dịch thẻ.\n- Tổ chức phát hành thẻ có trách nhiệm giải quyết yêu cầu tra soát và trả lời cho khách hàng trong thời hạn do các bên liên quan thỏa thuận, phù hợp với quy định của pháp luật. Trường hợp liên quan đến tổ chức thanh toán thẻ, tổ chức phát hành thẻ phải thông báo ngay cho tổ chức thanh toán thẻ và phối hợp với tổ chức thanh toán thẻ, các bên liên quan để giải quyết.\n- Khách hàng không đồng ý với kết quả tra soát của tổ chức phát hành thẻ, có quyền khởi kiện theo quy định của pháp luật."}, {"question": "Quy định về giải quyết vấn đề khi toàn bộ tài khoản của khách hàng biến mất, số dư còn lại trong tài khoản là 0?", "answer": "Điều 20 Thông tư 19/2016/TT-NHNN cũng quy định về thời hạn yêu cầu tra soát và trả lời tra soát:\n- Tổ chức phát hành thẻ quy định cụ thể thời hạn khách hàng phải gửi yêu cầu tra soát, nhưng không được ít hơn 60 ngày kể từ ngày phát sinh giao dịch yêu cầu tra soát.\n- Tổ chức thanh toán thẻ có trách nhiệm trả lời yêu cầu tra soát của chủ thẻ trong thời hạn tối đa là 05 ngày làm việc đối với giao dịch qua ATM đặt tại Việt Nam và 10 ngày làm việc đối với giao dịch qua POS/mPOS đặt tại Việt Nam; hoặc theo thỏa thuận giữa các bên liên quan đối với các giao dịch còn lại kể từ ngày nhận được yêu cầu từ tổ chức phát hành thẻ."}], "extras": {"page": 430}}