{"url": "https://thuvienphapluat.vn/hoi-dap-phap-luat/31F9C-hd-dai-hoi-thanh-vien-ngan-hang-hop-tac-xa.html", "data": [{"question": "Đại hội thành viên ngân hàng hợp tác xã được quy định như thế nào? ", "answer": "Đại hội thành viên ngân hàng hợp tác xã được quy định tại Điều 37 Thông tư 31/2012/TT-NHNN. Đây là cơ quan có quyền quyết định cao nhất của ngân hàng hợp tác xã, thực hiện các nhiệm vụ và quyền hạn theo Điều 80 Luật các tổ chức tín dụng. Đại hội thường niên phải được tổ chức mỗi năm một lần trong vòng ba tháng kể từ ngày kết thúc năm tài chính. Đại hội bất thường được triệu tập bởi Hội đồng quản trị trong các trường hợp sau: nếu họ xét thấy cần thiết vì lợi ích của ngân hàng hợp tác xã, theo yêu cầu bằng văn bản của ít nhất một phần ba tổng số thành viên, theo yêu cầu của Ban kiểm soát (Điều 84 Luật các tổ chức tín dụng), hoặc theo yêu cầu của Ngân hàng Nhà nước nếu có sự kiện ảnh hưởng đến an toàn hoạt động của ngân hàng hợp tác xã. Thông tin chi tiết có thể tham khảo thêm tại Thông tư 31/2012/TT-NHNN."}], "extras": {"page": 323}}