{"url": "https://thuvienphapluat.vn/hoi-dap-phap-luat/2D87C-hd-khai-truong-hoat-dong-to-chuc-tin-dung-phi-ngan-hang.html", "data": [{"question": "Khai trương hoạt động tổ chức tín dụng phi ngân hàng được quy định như thế nào?", "answer": "Tổ chức tín dụng phi ngân hàng được quy định tại Điều 10 Thông tư 30/2015/TT-NHNN. Theo đó:\n- Tổ chức tín dụng phi ngân hàng chỉ được tiến hành hoạt động kể từ ngày khai trương.\n- Để khai trương, tổ chức phải đảm bảo đủ các điều kiện quy định tại Khoản 2 Điều 26 Luật các tổ chức tín dụng.\n- Tổ chức tín dụng phi ngân hàng phải gửi thông báo về việc đáp ứng các điều kiện khai trương hoạt động đến Cục Thanh tra, giám sát ngân hàng (nếu có trụ sở chính tại nơi có Cục) hoặc Ngân hàng Nhà nước chi nhánh tỉnh, thành phố (nếu không có trụ sở tại nơi có Cục) ít nhất 15 ngày trước ngày dự kiến khai trương.\n- Tổ chức tín dụng phi ngân hàng phải tiến hành khai trương hoạt động trong thời hạn 12 tháng kể từ ngày được cấp giấy phép. Nếu quá thời hạn này mà không khai trương, Ngân hàng Nhà nước sẽ thu hồi giấy phép."}], "extras": {"page": 355}}