{"url": "https://thuvienphapluat.vn/hoi-dap-phap-luat/33BA9-hd-tap-the-co-so-cua-ngan-hang-nha-nuoc-la-nhung-don-vi-nao.html", "data": [{"question": "Tập thể cơ sở của Ngân hàng Nhà nước được quy định như thế nào?", "answer": "Tập thể cơ sở của Ngân hàng Nhà nước bao gồm các Vụ, Cục, Văn phòng thuộc Cơ quan Thanh tra, giám sát ngân hàng và các Chi cục thuộc Cục. Điều này được quy định tại Điểm b Khoản 1 Điều 3 của Thông tư 02/2015/TT-NHNN hướng dẫn công tác thi đua, khen thưởng trong ngành Ngân hàng, ban hành ngày 7/01/2015 bởi Thống đốc Ngân hàng Nhà nước.\n Ngoài ra, Thông tư này cũng quy định về các tập thể lớn và tập thể nhỏ trong ngành Ngân hàng, bao gồm các tổ chức tín dụng trong nước, nước ngoài, khối đào tạo, các doanh nghiệp do Ngân hàng Nhà nước quản lý và cơ quan thường trực của các hiệp hội do Ngân hàng Nhà nước quản lý."}], "extras": {"page": 284}}