{"url": "https://thuvienphapluat.vn/hoi-dap-phap-luat/3E58B-hd-quy-dinh-noi-bo-ve-quan-ly-thanh-khoan-cua-to-chuc-tai-chinh-vi-mo.html", "data": [{"question": "Quy định nội bộ về quản lý thanh khoản của tổ chức tài chính vi mô như thế nào?", "answer": "Điều 7 Thông tư 33/2015/TT-NHNN quy định nội bộ về quản lý thanh khoản của tổ chức tài chính vi mô, bao gồm: \n\n1. Hội đồng thành viên của tổ chức tài chính vi mô phải ban hành, rà soát, và sửa đổi quy định nội bộ về quản lý thanh khoản ít nhất một năm một lần.\n\n2. Quy định nội bộ về quản lý thanh khoản bao gồm những nội dung chính như phân công cán bộ theo dõi việc bảo đảm khả năng chi trả, phương án thực hiện chi trả tiền gửi, và các quy định về quản lý ngân quỹ, thu chi, và nguồn vốn hàng ngày.\n\n3. Trong thời hạn 10 ngày làm việc kể từ ngày ban hành hoặc sửa đổi quy định nội bộ, tổ chức tài chính vi mô phải gửi trực tiếp hoặc bằng đường bưu điện cho Ngân hàng Nhà nước chi nhánh ở tỉnh, thành phố trực thuộc Trung ương."}], "extras": {"page": 182}}